scat.py
scat-0.1.4.dist-info/DESCRIPTION.rst
scat-0.1.4.dist-info/METADATA
scat-0.1.4.dist-info/RECORD
scat-0.1.4.dist-info/WHEEL
scat-0.1.4.dist-info/entry_points.txt
scat-0.1.4.dist-info/metadata.json
scat-0.1.4.dist-info/top_level.txt
