Metadata-Version: 2.0
Name: scat
Version: 0.1.4
Summary: Schrödinger's cat
Home-page: https://github.com/ivanov/scat
Author: Paul Ivanov
Author-email: pi@berkeley.edu
License: BSD
Platform: UNKNOWN
